[{"Area":"State - JAMMU & KASHMIR","Males":853110,"Females":531858},{"Area":"State - HIMACHAL PRADESH","Males":586898,"Females":447304},{"Area":"State - PUNJAB","Males":1920912,"Females":1918426},{"Area":"State - CHANDIGARH","Males":222988,"Females":189084},{"Area":"State - UTTARAKHAND","Males":1137926,"Females":866868},{"Area":"State - HARYANA","Males":2367698,"Females":1621502},{"Area":"State - NCT OF DELHI","Males":3272154,"Females":2564230},{"Area":"State - RAJASTHAN","Males":4923844,"Females":2129238},{"Area":"State - UTTAR PRADESH","Males":14172892,"Females":7623518},{"Area":"State - BIHAR","Males":4942916,"Females":1528380},{"Area":"State - SIKKIM","Males":49624,"Females":36072},{"Area":"State - ARUNACHAL PRADESH","Males":117646,"Females":56228},{"Area":"State - NAGALAND","Males":193026,"Females":137062},{"Area":"State - MANIPUR","Males":356894,"Females":231376},{"Area":"State - MIZORAM","Males":112874,"Females":77918},{"Area":"State - TRIPURA","Males":215112,"Females":116480},{"Area":"State - MEGHALAYA","Males":154040,"Females":155884},{"Area":"State - ASSAM","Males":1436654,"Females":823984},{"Area":"State - WEST BENGAL","Males":6927954,"Females":3782594},{"Area":"State - JHARKHAND","Males":2079950,"Females":984390},{"Area":"State - ODISHA","Males":2607974,"Females":1323804},{"Area":"State - CHHATTISGARH","Males":1598538,"Females":834638},{"Area":"State - MADHYA PRADESH","Males":4622866,"Females":2559912},{"Area":"State - GUJARAT","Males":4166996,"Females":2776594},{"Area":"State - DAMAN & DIU","Males":17548,"Females":9150},{"Area":"State - DADRA & NAGAR HAVELI","Males":27760,"Females":15798},{"Area":"State - MAHARASHTRA","Males":11461646,"Females":7549388},{"Area":"State - ANDHRA PRADESH","Males":8250748,"Females":4365012},{"Area":"State - KARNATAKA","Males":5599160,"Females":3393742},{"Area":"State - GOA","Males":154020,"Females":150242},{"Area":"State - LAKSHADWEEP","Males":5364,"Females":3212},{"Area":"State - KERALA","Males":2374728,"Females":2949420},{"Area":"State - TAMIL NADU","Males":6990768,"Females":5155390},{"Area":"State - PUDUCHERRY","Males":174144,"Females":135424},{"Area":"State - ANDAMAN & NICOBAR ISLANDS","Males":27664,"Females":21496}]